TZnew
