Metadata-Version: 2.1
Name: TZnew
Version: 0.0.1
Summary: abc
Home-page: UNKNOWN
Author-email: anariem@mail.ru
License: UNKNOWN
Platform: UNKNOWN
